CHANGES.txt
LICENSE.txt
MANIFEST.in
README.rst
setup.py
bin/wrap.sh
pppack/__init__.py
pppack/pppack.py
pppack.egg-info/PKG-INFO
pppack.egg-info/SOURCES.txt
pppack.egg-info/dependency_links.txt
pppack.egg-info/requires.txt
pppack.egg-info/top_level.txt
pppack/lib/__init__.py
pppack/lib/chebyshev_interp_1d.so
pppack/lib/divdif.so
pppack/lib/pppack.so
src/divdif/divdif-f2pywrappers.f
src/divdif/divdifmodule.c