Metadata-Version: 1.1
Name: pppack
Version: 1.1.0.post1
Summary: A Python Piecewise Polynomial Package
Home-page: https://github.com/ndarmage/pppack
Author: Daniele Tomatis
Author-email: daniele.tomatis@gmail.com
License: MIT
Keywords: multivariate polynomial splines fortran
Platform: UNKNOWN
Classifier: Development Status :: 3 - Alpha
Classifier: Environment :: Console
Classifier: Intended Audience :: Science/Research
Classifier: Intended Audience :: Education
Classifier: Intended Audience :: Developers
Classifier: License :: OSI Approved :: MIT License
Classifier: Natural Language :: English
Classifier: Programming Language :: Python :: 2.7
Classifier: Topic :: Software Development :: Build Tools
Classifier: Programming Language :: Fortran
Classifier: Topic :: Scientific/Engineering
Classifier: Topic :: Software Development :: Libraries :: Python Modules
